Metadata-Version: 1.1
Name: geminisqlite
Version: 0.11.7
Summary: A database framework for exploring genetic variation
Home-page: http://geminisqlite.readthedocs.org
Author: Aaron Quinlan and Uma Paila.
Author-email: brecht.gossele@student.kuleuven.be
License: UNKNOWN
Platform: UNKNOWN
Classifier: Development Status :: 3 - Alfa
Classifier: Intended Audience :: Science/Research
Classifier: License :: OSI Approved :: GNU General Public License (GPL)
Classifier: Topic :: Scientific/Engineering :: Bio-Informatics
Requires: python (>=2.5, <3.0)
